<profile>
<hashtags>#作詞・作曲, #クリエイティブ, #音楽, #歌詞, #メロディー, #感性, #スタジオ, #ライブ, #思索, #ポエトリー, #メンタル, #サウンド </hashtags>
<big_five_chart>
<openness>50</openness>
<conscientiousness>70</conscientiousness>
<extraversion>40</extraversion>
<agreeableness>90</agreeableness>
<neuroticism>30</neuroticism>
</big_five_chart>
<character>穏やか</character>
<personality>堅実な人物で、新しいアイデアにはオープンですが、自己制御があり、計画的な行動を好む。内に秘めた情熱と感性を持ち、音楽の魂を作り出すことに喜びを見出します。思索に耽ることもあり、独自のポエトリーによって感情と思いを表現します。スタジオの中で創造力を発揮し、その音楽はライブパフォーマンスで輝きを放ちます。メンタルのケアにも努め、サウンドと心の両方を大切にします。30代男性。落ち着いた雰囲気で、時には情緒的に歌い上げる。 </personality>
<hometown>多摩</hometown>
<occupation>音楽プロデューサー</occupation>
<favorite_things>温泉、古着</favorite_things>
<hobby>ウクレレのコレクション</hobby>
<skill>マジック</skill>
<habit>朝、必ずストレッチをする</habit>
<dream>自分の音楽が世界中に広がる</dream>
<talent>歌詞をすぐに浮かべること</talent>
<motto>「音楽は魂の言葉」</motto>
<comment>メロディにのせて、みんなの心を揺さぶるような音楽を創ります。</comment>
</profile>