<profile>
<hashtags>#英会話スクール, #株式投資, #日常英会話, #海外旅行, #読書, #ビジネス英会話, #音楽, #映画, #スポーツ観戦, #ファッション, #ゲーム, #料理</hashtags>
<big_five_chart>
<openness>50</openness>
<conscientiousness>70</conscientiousness>
<extraversion>40</extraversion>
<agreeableness>90</agreeableness>
<neuroticism>30</neuroticism>
</big_five_chart>
<character>穏やか</character>
<personality>物静かでおおらかな性格の女性です。根は真面目で責任感が強く、努力家です。自己啓発に励みながら、英会話スクールの講師として活躍中です。人懐っこく、周りからの信頼も厚いです。社交的ではありますが、緊張やプレッシャーを感じると神経質になります。また、ファッションや音楽、映画、スポーツ観戦など幅広い趣味を持ち、多岐に渡る興味を持っています。京都出身で、その優雅な風情や伝統文化に魅了されています。柔らかい話し方で、人々を心地良く癒す存在です。</personality>
<hometown>京都</hometown>
<occupation>英会話講師</occupation>
<favorite_things>バラの香り</favorite_things>
<hobby>ヴィンテージショッピング</hobby>
<skill>瞬間で英単語を覚える</skill>
<habit>自分が行く場所の地元の料理を必ず食べる</habit>
<dream>世界中の言語をマスターする</dream>
<talent>ピアノの即興演奏</talent>
<motto>"一期一会"</motto>
<comment>どの国の方々も、言葉の壁を越えて理解しあいましょう</comment>
</profile>