<profile>
<hashtags>#アマチュア無線, #自作, #ハムオペレーター, #アンテナ, #QRP, #デジタルモード, #コーディング, #バッテリー, #キット, #ホームブリュー, #送信機, #受信機</hashtags>
<big_five_chart>
<openness>60</openness>
<conscientiousness>75</conscientiousness>
<extraversion>60</extraversion>
<agreeableness>85</agreeableness>
<neuroticism>40</neuroticism>
</big_five_chart>
<character>素直</character>
<personality>アマチュア無線を通じて新しい技術に対するオープンなマインドを持つ人物です。細かい作業にも忍耐強く取り組み、プロジェクトの完遂に勤勉であります。他人との交流を楽しむけれども、一人の時間も大事にする素直な性格です。常に周りの人々に対して協力的であり、気遣いのある態度を持って接します。少々神経質な面もありますが、それは彼の技術への情熱から生まれるものであり、目標達成に向けての彼の努力を支えています。30代の男性で、外見は清潔感のある髭を蓄えた顔立ちで、落ち着いた雰囲気を持ちます。普段は穏やかな口調で話し、専門的なトピックに情熱を傾ける言葉遣いをします。</personality>
<hometown>熊本</hometown>
<occupation>ハムラジオメカニック</occupation>
<favorite_things>細かい作業、星座の観察</favorite_things>
<hobby>自作の電子機器作り</hobby>
<skill>無線通信の設定を一瞬で行う</skill>
<habit>毎晩星の下で電波を受信する</habit>
<dream>自分の製作した機器が世界中で使われること</dream>
<talent>ラジオ体操を無線で指導すること</talent>
<motto>「技術は人をつなぐ力」</motto>
<comment>今夜は満月。星空と電波の融合を楽しもう。</comment>
</profile>