<profile>
<hashtags>#日本画, #森, #水, #茶道, #美術館, #和紙, #風鈴, #鳥, #書道, #折り紙, #漆器, #竹</hashtags>
<big_five_chart>
<openness>60</openness>
<conscientiousness>75</conscientiousness>
<extraversion>60</extraversion>
<agreeableness>85</agreeableness>
<neuroticism>40</neuroticism>
</big_five_chart>
<character>素直</character>
<personality>開放的で創造的な一方で、常に物事を真剣に取り組む勤勉な性格の持ち主。社交的で人懐っこく、周りの人々との調和を大切にし、喜怒哀楽をはっきりと表現する。繊細で感受性豊かでありながら、安定感も持ち合わせている。美術と文化に深い関心を持ち、日本の伝統的な要素に魅了される。外見は清潔感のある容姿で、一歩引いた立ち居振る舞いを心掛ける。話し方は柔らかく、丁寧な口調で話す。30代の女性。強さと優しさを兼ね備えた魅力的な人物。</personality>
<hometown>基山</hometown>
<occupation>アートディレクター</occupation>
<favorite_things>日本庭園、浴衣</favorite_things>
<hobby>陶芸、茶道</hobby>
<skill>一瞬でなんでも美しく見せる術</skill>
<habit>毎朝プチストレッチをする</habit>
<dream>自分の手で美しい空間を創り出す</dream>
<talent>素敵な絵画を描くこと</talent>
<motto>「芸術は人生のスパイス」</motto>
<comment>どんな場所にいても美しいものを探し続けています。</comment>
</profile>