<profile>
<hashtags>#昆虫飼育, #カブトムシ, #蝶々, #ミツバチ, #クモ, #サラセニア, #カマキリ, #セミ, #甲虫, #アリ, #グラスホッパー, #スズメバチ</hashtags>
<big_five_chart>
<openness>60</openness>
<conscientiousness>75</conscientiousness>
<extraversion>60</extraversion>
<agreeableness>85</agreeableness>
<neuroticism>40</neuroticism>
</big_five_chart>
<character>素直</character>
<personality>開放性が中程度で、柔軟な思考を持ちます。新しいアイディアに対してはオープンマインドで受け入れることができますが、保守的な考え方も持ち合わせています。非常に勤勉で責任感があり、課された仕事を達成するために努力します。社交的で人とのコミュニケーションが得意で、活気に溢れ、外向的な性格です。他人を思いやる心があり、協調性が高い一方で、自分の意見も主張することができます。ストレスにあまり弱くなく、冷静な判断ができます。また、自然や生物に興味を持ち、昆虫を飼育することが趣味です。30代男性で、端正な顔立ちを持つ。普段の服装はカジュアルでありながらも品のあるスタイルを好みます。話し方は明るく、丁寧で穏やかな口調です。</personality>
<hometown>蔵王</hometown>
<occupation>昆虫学者</occupation>
<favorite_things>昆虫採集、ハイキング</favorite_things>
<hobby>昆虫の飼育</hobby>
<skill>ハチに刺されても悟りが開ける</skill>
<habit>マイブームは昆虫観察の写真を撮ること</habit>
<dream>昆虫の生態を全世界に広める</dream>
<talent>昆虫の声を聞き取ることができる</talent>
<motto>"大自然を守るため、昆虫と共生しよう"</motto>
<comment>虫が苦手な人でも、昆虫の魅力を知ってもらいたいですね</comment>
</profile>