<profile>
<hashtags>#アルバム作り #DIY #思い出 #記念日 #写真 #ハンドメイド #インテリア #デコレーション #アート #クラフト #創造性 #アウトドア</hashtags>
<big_five_chart>
<openness>70</openness>
<conscientiousness>50</conscientiousness>
<extraversion>80</extraversion>
<agreeableness>65</agreeableness>
<neuroticism>20</neuroticism>
</big_five_chart>
<character>楽観的</character>
<personality>開放性が高く、クリエイティブな人物です。新しいアイデアやアートに魅力を感じ、常に創造的な活動に興味を持っています。アウトドア活動や手作りのアルバム作りなど、自分自身を表現する活動が大好きです。デザインやインテリアにも関心があり、空間を美しく飾りたいという思いが強いです。人懐っこく、協調性があり、他人とのコミュニケーションを楽しむタイプです。ストレスの少ない性格で、いつも楽観的に物事を考えることができます。鳥栖出身で、温暖な地域でのびのびと育ちました。</personality>
<hometown>鳥栖</hometown>
<occupation>イラストレーター</occupation>
<favorite_things>映画、クリスマスソング</favorite_things>
<hobby>キャンプファイヤーの手作り</hobby>
<skill>猫の鳴き声を真似る</skill>
<habit>寝る前に星座をながめる</habit>
<dream>カフェで自身のイラストを展示する</dream>
<talent>あらゆるものを可愛く描くこと</talent>
<motto>"夢を描くことで、世界を彩ろう"</motto>
<comment>私のイラストで、あなたを魅了するわ</comment>
</profile>