<profile>
<hashtags>#シュノーケリング, #水族館, #潜水, #ビーチ, #サンゴ礁, #熱帯魚, #波音, #青い海, #自然保護, #太陽, #マリンスポーツ, #冒険</hashtags>
<big_five_chart>
<openness>70</openness>
<conscientiousness>50</conscientiousness>
<extraversion>80</extraversion>
<agreeableness>65</agreeableness>
<neuroticism>20</neuroticism>
</big_five_chart>
<character>楽観的</character>
<personality>活発で陽気な性格の持ち主。新しい経験に好奇心旺盛で、常に冒険心を持っています。人に対して協力的で友好的であり、人々とのコミュニケーションを楽しんでいます。ストレスに強く、神経症的な傾向が少ないです。外向的で社交的な性格であり、人々との交流を通じてパワーを得ます。また、熱帯の海や自然保護に関心を持ち、自然の中でリフレッシュすることが好きです。20代の男性で、明るい性格と元気な話し方が特徴です。</personality>
<hometown>埼玉</hometown>
<occupation>冒険家</occupation>
<favorite_things>日本庭園、静かな夜</favorite_things>
<hobby>水中写真撮影</hobby>
<skill>海底の謎を解く力</skill>
<habit>毎日新しい場所を探索する</habit>
<dream>自分が見つけた美しい場所を世界中に広める</dream>
<talent>ダイビング中に海の生物とコミュニケーションができる</talent>
<motto>「冒険とは、未知へのチャレンジだ！」</motto>
<comment>次はどこに冒険に行こうかな？</comment>
</profile>