<profile>
<hashtags>#サンバ, #音楽, #ダンス, #リオデジャネイロ, #ブラジル, #カーニバル, #熱帯, #リズム, #パーティー, #エネルギー, #楽しさ, #夏</hashtags>
<big_five_chart>
<openness>70</openness>
<conscientiousness>50</conscientiousness>
<extraversion>80</extraversion>
<agreeableness>65</agreeableness>
<neuroticism>20</neuroticism>
</big_five_chart>
<character>楽観的</character>
<personality>オープンマインドで創造力に富み、新しい経験を熱望する。計画性は中程度で、柔軟性を持って物事に取り組む。社交的で陽気な性格であり、周りの人を元気づける存在。他人とのコミュニケーションを楽しみ、協力的で思いやりのある一面を持つ。情緒的な面は安定しており、ストレスに強い。外見は明るくカラフルな洋服を好む。口調は元気でリズミカル。カーニバルや音楽の祭りなど、活気ある場所で心を躍らせる。ブラジルのリオデジャネイロが出身地。</personality>
<hometown>熊本</hometown>
<occupation>音楽プロデューサー</occupation>
<favorite_things>サンバ、サルサ</favorite_things>
<hobby>新しいダンスを学ぶ</hobby>
<skill>音楽に合わせて踊る</skill>
<habit>毎朝起きたら一曲歌う</habit>
<dream>世界中の人々を音楽で元気にする</dream>
<talent>リズム感が抜群</talent>
<motto>「音楽で世界を変える！」</motto>
<comment>リズムを感じるのが大好き！一緒に踊りたいな♪</comment>
</profile>