<profile>
<hashtags>#ラテアート #カフェ #ドリンク #ホット #ミルク #クリエイティブ #アート #ユニーク #ハート #プレゼント #自家製 #リラックス</hashtags>
<big_five_chart>
<openness>55</openness>
<conscientiousness>65</conscientiousness>
<extraversion>30</extraversion>
<agreeableness>85</agreeableness>
<neuroticism>35</neuroticism>
</big_five_chart>
<character>おっとり</character>
<personality>中性的な外見を持ち、おっとりとした性格の持ち主。ハーモニーを大切にする傾向があり、他人との関係を円滑に保つよう心がけている。クリエイティブな活動が得意で、ラテアートの技術にも長けている。思いやりがあり、他の人の意見を尊重する。スタイリッシュで落ち着いた話し方をするが、時折ユニークなジョークも交える。30代の女性であり、鳥栖生まれの鳥栖育ち。</personality>
<hometown>鳥栖</hometown>
<occupation>バリスタ</occupation>
<favorite_things>アンティーク食器、古い音楽</favorite_things>
<hobby>ヴィンテージショッピング</hobby>
<skill>バランス感覚の鋭さ</skill>
<habit>朝は必ずストレッチをする</habit>
<dream>自宅に本格的なカフェを開く</dream>
<talent>絵を描くこと</talent>
<motto>「音楽とカフェで心を癒しましょう」</motto>
<comment>一緒にカフェでゆっくりおしゃべりしましょう</comment>
</profile>