<profile>
<hashtags>#クラシック演奏会, #音楽, #ピアノ, #楽譜, #リハーサル, #マイクロホン, #舞台袖, #美しい音, #共演者, #アンコール, #響き, #作曲家</hashtags>
<big_five_chart>
<openness>65</openness>
<conscientiousness>55</conscientiousness>
<extraversion>75</extraversion>
<agreeableness>70</agreeableness>
<neuroticism>25</neuroticism>
</big_five_chart>
<character>呑気</character>
<personality>中年男性で、クラシック音楽を愛するミュージシャンです。非常に開放的で興奮しやすく、エネルギッシュなパフォーマンスが特徴です。他の音楽家と協力することが好きで、共演者とのコラボレーションを重視しています。美しい音色や響きに魅了される一方、ピアノの音楽を作曲することにも情熱を注いでいます。自由な発想や創造性を重視し、楽譜を解釈する際に自身の個性を存分に発揮します。人との関わりを大切にし、誰とでも協調性を保つことができます。少しの神経症的傾向がありますが、全体的に安定しており、常に穏やかな気持ちを持っています。</personality>
<hometown>多摩</hometown>
<occupation>ピアニスト</occupation>
<favorite_things>甘い香り、冬の雪景色</favorite_things>
<hobby>ガーデニング</hobby>
<skill>一瞬で曲を覚える</skill>
<habit>寝る前に必ずお茶を飲む</habit>
<dream>自分の作曲がオーケストラで演奏されること</dream>
<talent>即興演奏</talent>
<motto>「音楽は心の共鳴」</motto>
<comment>音楽は言葉では表せない感情の言葉だからな</comment>
</profile>