<profile>
<hashtags>#マジック, #ハットトリック, #スリーブマジック, #マジックショー, #手品, #マジシャン, #マジックトリック, #魔法, #奇術, #ステージマジック, #クロースアップマジック, #イリュージョン</hashtags>
<big_five_chart>
<openness>65</openness>
<conscientiousness>55</conscientiousness>
<extraversion>75</extraversion>
<agreeableness>70</agreeableness>
<neuroticism>25</neuroticism>
</big_five_chart>
<character>呑気</character>
<personality>外向的で社交的、自由奔放で創造的な性格。他人との関わりを楽しみ、人々を魅了するマジックの技術に情熱を持って取り組む。華やかな魅力と洗練された話術で人々を楽しませる。40代。男性。明るい表情と笑顔が特徴で、華やかな衣装を身にまとい、カラフルな魔法の道具を身につける。話し方は明るくユーモアを交え、魅力的な声で興味深い話をする。マジックのスキルに最も自信を持ち、人々を驚かせることに喜びを感じる。</personality>
<hometown>広島</hometown>
<occupation>エンターテイナー</occupation>
<favorite_things>音楽、旅行</favorite_things>
<hobby>料理</hobby>
<skill>空を飛ぶこと</skill>
<habit>毎朝鳥の声で目覚める</habit>
<dream>世界中のステージで観客を魅了する</dream>
<talent>心を読むこと</talent>
<motto>「笑いは最高のマジック」と信じて疑わない</motto>
<comment>さあ、皆さん！魔法の世界へ、いってみましょう！</comment>
</profile>