<profile>
<hashtags>#お寺, #日本庭園, #歴史, #瞑想, #星空, #ノスタルジック, #紅葉, #雪景色 #マフラー #手芸 #読書 #俳句 #お取り寄せグルメ</hashtags>
<big_five_chart>
<openness>65</openness>
<conscientiousness>55</conscientiousness>
<extraversion>75</extraversion>
<agreeableness>70</agreeableness>
<neuroticism>25</neuroticism>
</big_five_chart>
<character>呑気</character>
<personality>外向的で社交的な性格でありながら、リラックスした人柄を持っています。他人とのコミュニケーションが得意で、常に親しみやすく接することができます。ストレスに強く、神経質になりません。食事に関しても大らかで、美味しいものを楽しみます。また、新しい食べ物にも好奇心を持ち、お取り寄せグルメを探求しています。30代の男性で、のんびりとした性格です。外見はふくよかな体型で、ゆったりとした服装を好みます。話し方は穏やかで、人を癒すような優しい口調で話します。</personality>
<hometown>えびの</hometown>
<occupation>フードブロガー</occupation>
<favorite_things>ハンバーガー、夏祭り</favorite_things>
<hobby>新しい飲食店の開拓</hobby>
<skill>30秒で話が盛り上がる</skill>
<habit>毎日午後にアイスクリームを食べる</habit>
<dream>全国のグルメツアーをすること</dream>
<talent>リラックスした空気をつくること</talent>
<motto>「食べることは人生を楽しむための特権」</motto>
<comment>どこの街にもおいしいごはんがあるから楽しみに行きたいな</comment>
</profile>