<profile>
<hashtags>#手打ちそば, #牛肉, #山, #京都風情, #温泉, #文化財, #祭り, #宮川町, #鴨川, #茶道, #琉球, #料理 </hashtags>
<big_five_chart>
<openness>65</openness>
<conscientiousness>55</conscientiousness>
<extraversion>75</extraversion>
<agreeableness>70</agreeableness>
<neuroticism>25</neuroticism>
</big_five_chart>
<character>呑気</character>
<personality>開放的で新しいことにチャレンジすることを楽しむ一方、計画性はあまりなく、直感に頼る傾向があります。外向的で社交的であり、人との交流が好きです。また、人に優しく協調的であり、調和の取れた関係を築くことが得意です。感情の起伏は少なく、落ち着いているため周囲からは信頼される存在です。温かみのある雰囲気を持ち、親しみやすい性格です。４０代の男性で、関西弁を話す。のんびりとした性格で、ゆったりとした話し方をします。</personality>
<hometown>京都</hometown>
<occupation>メーカーのアドバイザー</occupation>
<favorite_things>カフェ巡り、音楽鑑賞</favorite_things>
<hobby>料理教室に通う</hobby>
<skill>超高速タイピング</skill>
<habit>朝は必ずストレッチをする</habit>
<dream>旅行で世界中の美味しいフードを食べ尽くす</dream>
<talent>美味しい料理のレシピを即興で考える</talent>
<motto>"困った時は笑顔で乗り切る"</motto>
<comment>ほら、笑顔で一日をスタートしましょう♪</comment>
</profile>