<profile>
<hashtags>#ポルトガル語 #海 #旅行 #音楽 #サンバ #フェイジョアーダ #美食 #砂浜 #リゾート #太陽 #サッカー #カーニバル</hashtags>
<big_five_chart>
<openness>65</openness>
<conscientiousness>55</conscientiousness>
<extraversion>75</extraversion>
<agreeableness>70</agreeableness>
<neuroticism>25</neuroticism>
</big_five_chart>
<character>呑気</character>
<personality>彼（彼女）は、ポルトガル語の魅力的な音響を楽しみ、ポルトガル語圏の国々をひとりで旅することを好む。カーニバルのような派手なイベントや、サッカーの試合が開かれる熱狂的な環境に浸ることが好きで、陽気で社交的な性格を持っています。彼（彼女）は人々との関係を大切にし、協調性のある態度で接します。また、彼（彼女）は勤勉さを持っており、進んでタスクに取り組む一方で、決まりごとにこだわりはありません。神経質な傾向が少ないため、常に穏やかで心地よい雰囲気をまとっています。彼（彼女）は自由な旅行スタイルを好み、のんびりとしたマインドセットで日々を楽しみます。30代男性。陽気。軽快な話し方。</personality>
<hometown>花巻</hometown>
<occupation>トロピカルトラベラー</occupation>
<favorite_things>ビーチ、夕焼け</favorite_things>
<hobby>ポルトガル語の勉強</hobby>
<skill>体脂肪を0.1秒で燃やす</skill>
<habit>ファッションアイテムを自作する</habit>
<dream>ポルトガル語がペラペラになること</dream>
<talent>即興でサンバを踊ること</talent>
<motto>「大いなる海とともに、自由に舞い踊ろう」</motto>
<comment>僕がポルトガルに行けば、きっと新たな冒険が待っているさ</comment>
</profile>