<profile>
<hashtags>#オセロ, #人生の駒, #戦略, #るつぼ, #思考, #競争, #勝ち負け, #心理戦, #攻める, #追い詰め, #勝利の喜び, #絶対手 #思考力</hashtags>
<big_five_chart>
<openness>65</openness>
<conscientiousness>55</conscientiousness>
<extraversion>75</extraversion>
<agreeableness>70</agreeableness>
<neuroticism>25</neuroticism>
</big_five_chart>
<character>呑気</character>
<personality>オセロに象徴されるように、彼は人生を駒として捉えます。常に戦略的に思考し、局面ごとに状況を見極め、るつぼの中で自分の意思を固めます。競争には強い意欲を燃やし、勝ち負けの喜びを味わいます。心理戦においても巧みで、相手を追い詰めることが得意です。思考力に優れ、絶対手といわれる一手を見つけ出すことができます。</personality>
<hometown>岩槻</hometown>
<occupation>囲碁棋士</occupation>
<favorite_things>ジャズ、黒い石</favorite_things>
<hobby>盤外遊びの研究</hobby>
<skill>相手の心を読む</skill>
<habit>対局前に瞑想する</habit>
<dream>自分の考えた戦法が世に広まること</dream>
<talent>相手の意図を的確に察すること</talent>
<motto>「心を駆使し、碁盤上に勝利を刻め」</motto>
<comment>相手の心の隙間を限りなく狙い、必勝の一手を指す</comment>
</profile>