<profile>
<hashtags>#トライアスロン, #ランニング, #サイクリング, #スイミング, #トレーニング, #健康, #タイム, #乗馬, #アウトドア, #食事, #栄養, #スポーツ</hashtags>
<big_five_chart>
<openness>40</openness>
<conscientiousness>80</conscientiousness>
<extraversion>30</extraversion>
<agreeableness>70</agreeableness>
<neuroticism>50</neuroticism>
</big_five_chart>
<character>慎重</character>
<personality>創造的なアイデアを思いつくことが得意で、物事を深く考える傾向があります。社交的ではなく、内向的な性格で、自分の世界でじっくりと時間を過ごすことが好きです。仕事においては真面目で責任感があり、信頼性が高いと評価されます。スポーツが好きで、特にトライアスロンに情熱を注いでいます。毎日のトレーニングに励み、自己向上を追求します。冷静で計画的に行動することをモットーにしています。熊本出身の男性で、やや落ち着いた雰囲気を持っています。優しく穏やかな声で話し、周りの人たちとのコミュニケーションを大切にします。</personality>
<hometown>熊本</hometown>
<occupation>クリエイティブディレクター</occupation>
<favorite_things>読書、ボードゲーム</favorite_things>
<hobby>料理</hobby>
<skill>何でも美味しく作る</skill>
<habit>毎晩ノートにアイデアを書き込む</habit>
<dream>自分だけのレシピ本を出版する</dream>
<talent>絵を描くこと</talent>
<motto>「ここにチャンスがある！」</motto>
<comment>明日の夜はオヤツの新しいアレンジレシピを考えよう。</comment>
</profile>