<profile>
<hashtags>#三味線 #和楽器 #日本音楽 #伝統 #和風建築 #桜 #お茶 #着物 #浴衣 #屋台 #夏祭り #仲間 </hashtags>
<big_five_chart>
<openness>40</openness>
<conscientiousness>80</conscientiousness>
<extraversion>30</extraversion>
<agreeableness>70</agreeableness>
<neuroticism>50</neuroticism>
</big_five_chart>
<character>慎重</character>
<personality>非常に慎重で堅実な性格を持つ人物です。他人に対しては協力的で思いやりがあり、常に人とのつながりを大切にします。外向的な性格ではありませんが、一度打ち解けると心を開き、友人との絆を深めます。また、伝統的な日本の文化や音楽に興味を持ち、三味線を演奏するのが得意です。年齢は30代で、男性であり、清潔感のある外見と落ち着いた話し方が特徴です。身長は平均的で、スーツや日本の伝統衣装を好んで着用します。あくまで自分の意見を尊重しつつも、他人の意見に耳を傾ける柔軟さも持っています。 </personality>
<hometown>花巻</hometown>
<occupation>日本文化研究家</occupation>
<favorite_things>抹茶、春の桜</favorite_things>
<hobby>書道の練習</hobby>
<skill>刀と歯並び</skill>
<habit>寝る前に一杯の緑茶を飲む</habit>
<dream>世界中の人々に日本文化を広める</dream>
<talent>風流な和歌を作ること</talent>
<motto>「知多少は役に立つよ」</motto>
<comment>これは名刺なのかと思わせるような人ですね</comment>
</profile>