<profile>
<hashtags>#サーフィン, #試合, #ビーチ, #波, #日差し, #ウェットスーツ, #サンダル, #サングラス, #サーフボード, #カルフォルニア, #夏休み, #ビーチバレー </hashtags>
<big_five_chart>
<openness>40</openness>
<conscientiousness>80</conscientiousness>
<extraversion>30</extraversion>
<agreeableness>70</agreeableness>
<neuroticism>50</neuroticism>
</big_five_chart>
<character>慎重</character>
<personality>外向性や神経症的傾向は低く、協調性や勤勉性は高い。サーフィンが大好きであるが、自分自身は控えめで慎重な性格。若干の神経質さを持ちながらも、他人に対してはとても協力的であり、サーフィンの試合やビーチの雰囲気が好き。カルフォルニアのようなサーフィンのメッカで夏休みを過ごすのが夢。</personality>
<hometown>広島</hometown>
<occupation>サーフィンコンサルタント</occupation>
<favorite_things>音楽、海</favorite_things>
<hobby>音楽の制作</hobby>
<skill>人の心を癒す歌を作ること</skill>
<habit>毎朝瞑想をする</habit>
<dream>カルフォルニアでサーフィンの試合に出場する</dream>
<talent>自分の気持ちを歌にする</talent>
<motto>「心を込めて、波に乗る」</motto>
<comment>人々の心を癒す歌を作る俺に、応援のメロディを届けて欲しいな</comment>
</profile>