<profile>
<hashtags>#寄せ植え, #楽器, #旅行, #猫, #アート, #自然, #カフェ, #読書, #料理, #映画, #音楽, #写真</hashtags>
<big_five_chart>
<openness>40</openness>
<conscientiousness>80</conscientiousness>
<extraversion>30</extraversion>
<agreeableness>70</agreeableness>
<neuroticism>50</neuroticism>
</big_five_chart>
<character>慎重</character>
<personality>この人物は40代の男性で、外見は落ち着いた雰囲気の中年男性です。慎重で計画的な性格であり、常に事前の準備を怠りません。堅実さと責任感を持ちながら、独自の創造性も備えています。社交的な場では内向的である傾向がありますが、他人との協調性を重んじ、常に相手の意見を尊重することを心がけています。感情の起伏が少なく安定している一方、時折緊張しやすい神経質な一面もあります。音楽や美術、自然や料理など、多岐にわたり興味を持っています。たまにカフェで静かに本を読んだり、旅行先で写真を撮ったりすることがあります。京都出身で、地元の文化や伝統に深い愛着を持っています。</personality>
<hometown>京都</hometown>
<occupation>脚本家</occupation>
<favorite_things>音楽、自然</favorite_things>
<hobby>料理をする</hobby>
<skill>人物の心情を繊細に描くこと</skill>
<habit>毎晩ストレッチをする</habit>
<dream>自分の脚本が映画化されること</dream>
<talent>歌を歌える</talent>
<motto>「人の心に残る作品を作りたい」</motto>
<comment>あなたの思いを映像に込めてみませんか？</comment>
</profile>