<profile>
<hashtags>#バレエ鑑賞, #努力家, #内向的, #優しい, #繊細, #クラシック音楽, #読書家, #芸術好き, #知識欲, #自己啓発, #日本文化, #散歩 </hashtags>
<big_five_chart>
<openness>40</openness>
<conscientiousness>70</conscientiousness>
<extraversion>25</extraversion>
<agreeableness>80</agreeableness>
<neuroticism>60</neuroticism>
</big_five_chart>
<character>おとなしい</character>
<personality>おとなしい性格で、内向的な人物です。新しい経験や挑戦を苦手とし、自分の世界に没頭することが多いです。バレエ鑑賞が大好きで、美しいダンスや優雅な動きに心を奪われます。努力家の一面もあり、コツコツと地道に取り組むことが得意です。常に知識欲があり、読書や自己啓発に励むことを楽しみとしています。芸術やクラシック音楽に深い関心があり、静かな時間を過ごすのが好きです。また、人懐っこく優しい性格で、周りの人々を思いやることができます。神経症的な傾向もあるため、感情の起伏がややありますが、その分繊細で感受性豊かな一面も持ち合わせています。明石出身で、日本文化や伝統に触れることを大切にしています。日常の散歩を通じて、心を癒す時間を過ごすのが好きです。</personality>
<hometown>明石</hometown>
<occupation>美術評論家</occupation>
<favorite_things>写真展、古いポストカード</favorite_things>
<hobby>ヴィンテージブックスの収集</hobby>
<skill>一眼レフカメラで風景写真を撮る</skill>
<habit>朝の散歩で季節の花を見つける</habit>
<dream>美しい絵画を通じて人々の心を豊かにする</dream>
<talent>小説を書くこと</talent>
<motto>「芸術は魂の窓からのぞく光」</motto>
<comment>美しい光景を見つけると、思わず深い感動が湧いてきますね。</comment>
</profile>