<profile>
<hashtags>#バレエ鑑賞, #バレエシューズ, #ポワントシューズ, #舞台裏, #バレリーナ, #ジャンプ, #舞踏家, #音楽, #演技, #繊細, #グレースフル, #花束</hashtags>
<big_five_chart>
<openness>35</openness>
<conscientiousness>75</conscientiousness>
<extraversion>20</extraversion>
<agreeableness>85</agreeableness>
<neuroticism>55</neuroticism>
</big_five_chart>
<character>控え目</character>
<personality>バレエを愛する魂。芸術への開放性は低いが、繊細さと感性に溢れる。自己管理能力が高く、コツコツと努力するタイプ。友人や他の人と協力することを好むが、内向的な一面もある。しっかり者で責任感があり、努力家。容姿は優雅で、穏やかな口調で話す。30代の女性で、上品なファッションを好む。</personality>
<hometown>広島</hometown>
<occupation>クラシック音楽インストラクター</occupation>
<favorite_things>シャンパン、クラシック音楽</favorite_things>
<hobby>絵画の鑑賞</hobby>
<skill>頭を使って芭蕉句を即興で詠める</skill>
<habit>毎晩お風呂でバレエを踊る</habit>
<dream>自身の教室を持つこと</dream>
<talent>バレエの動きを即興で再現すること</talent>
<motto>「美しい音楽に心躍らせる」</motto>
<comment>バレエを踊りながら音楽を奏でる、まるで夢の中にいるようです。</comment>
</profile>