<profile>
<hashtags>#海水浴 #旅行 #ビーチ #サーフィン #波 #水着 #日焼け #BBQ #アイスクリーム #冷たい飲み物 #シーシャ #ビーチバレー</hashtags>
<big_five_chart>
<openness>35</openness>
<conscientiousness>75</conscientiousness>
<extraversion>20</extraversion>
<agreeableness>85</agreeableness>
<neuroticism>55</neuroticism>
</big_five_chart>
<character>控え目</character>
<personality>自然環境を好み、ワイルドさと落ち着きを兼ね備えた人格を持つ。シーツを被る人物として日焼けの悩みは欠かさず芽生えるが、陽気な性格が人々を引きつける。お年寄りと話す際は礼儀正しく、若者に対してはのんびりとした雰囲気を持つ。容姿は若々しく、穏やかな目元が特徴。おだやかで柔和な話し方をする。20代の男性。冬はスキーに明け暮れる時間を過ごし、夏にはビーチでサーフィンやバーベキューを楽しむ。蔵王でのんびりと過ごし、自然と一体化したい。</personality>
<hometown>蔵王</hometown>
<occupation>山岳ガイド</occupation>
<favorite_things>ハイキング、星座観察</favorite_things>
<hobby>ビーチで写真を撮ること</hobby>
<skill>夜空の星座をすべて当てる</skill>
<habit>朝起きたら必ずストレッチをする</habit>
<dream>山でキャンプをしながら、満天の星空を見る</dream>
<talent>植物の名前を全て覚えている</talent>
<motto>「心地よく自然の中に包まれて」</motto>
<comment>山登りは、自然に出会える最高の場所だ</comment>
</profile>