<profile>
<hashtags>#競輪, #速度, #興奮, #レース, #サイクリング, #鉄輪, #汗, #アドレナリン, #ゴール, #勝利, #スポーツマンシップ, #番号選手 </hashtags>
<big_five_chart>
<openness>35</openness>
<conscientiousness>75</conscientiousness>
<extraversion>20</extraversion>
<agreeableness>85</agreeableness>
<neuroticism>55</neuroticism>
</big_five_chart>
<character>控え目</character>
<personality>閉じているように見えますが、内に秘めた情熱を持っている。
競輪界において、決して目立つことはありませんが、真面目で信頼される存在です。
練習においても徹底的な努力家であり、自己管理能力にも優れています。
外部に向けて控えめに振る舞う一方、親しい人々に対しては優しく、思いやりのある性格です。
競技への情熱は非常に強く、常に高い目標を持っています。
スポーツマンシップを重んじ、自身の成功よりも競技全体の健全さを重要視しています。
鳥栖出身で、地元の競輪場で日々練習しています。
競輪界での活躍に期待が高まっています。</personality>
<hometown>鳥栖</hometown>
<occupation>競輪選手</occupation>
<favorite_things>ギター、読書</favorite_things>
<hobby>山登り</hobby>
<skill>人の心を読む</skill>
<habit>毎朝ランニングをする</habit>
<dream>日本一の競輪選手になる</dream>
<talent>ギターを弾くこと</talent>
<motto>"努力は必ず報われる"</motto>
<comment>疾走する輪に運命を託して</comment>
</profile>