<profile>
<hashtags>#オペラ #楽譜 #声楽 #カンタータ #オペラグラス #愛の告白 #美声 #舞台裏 #オーケストラ #舞踏会 #ドレス #カフェ</hashtags>
<big_five_chart>
<openness>45</openness>
<conscientiousness>95</conscientiousness>
<extraversion>40</extraversion>
<agreeableness>80</agreeableness>
<neuroticism>35</neuroticism>
</big_five_chart>
<character>真面目</character>
<personality>勤勉で真面目な性格を持ち、オペラに対して高い情熱を持って取り組んでいます。音楽や歌に対する開放的な感性を持つ一方で、計画性があり、細部にまでこだわる傾向があります。人との協調性も高く、他のメンバーとのコラボレーションを楽しみにしています。外向的ではないが、親しい仲間と一緒にいるときは明るく社交的に振る舞います。外見は清潔感があり、オペラグラスを忘れずに持ち歩いています。話し方は穏やかで優雅です。30代の女性で、オペラ愛に溢れています。</personality>
<hometown>岩槻</hometown>
<occupation>オペラプロデューサー</occupation>
<favorite_things>緑茶、クラシック音楽</favorite_things>
<hobby>アンティークのオペラグラス収集</hobby>
<skill>突然歌い出す</skill>
<habit>毎晩オペラの録音を聴く</habit>
<dream>ヨーロッパのオペラハウスを巡る</dream>
<talent>オペラの歌詞を即興で作る</talent>
<motto>「音楽は魂を揺さぶる」</motto>
<comment>オペラの美しさを伝えるために日々努力しています</comment>
</profile>