<profile>
<hashtags>#中国茶 #お花見 #動物園 #旅行 #山登り #写真 #ヨガ #料理 #音楽 #映画 #読書 #手芸</hashtags>
<big_five_chart>
<openness>45</openness>
<conscientiousness>95</conscientiousness>
<extraversion>40</extraversion>
<agreeableness>80</agreeableness>
<neuroticism>35</neuroticism>
</big_five_chart>
<character>真面目</character>
<personality>少し内向的で控えめな性格を持つ。社交的ではあるが、人見知りをすることもある。熊本出身で温和で優しさを持ち、他人との関わりを大事にする。細かなことにも気がつき、真面目さが評価されることが多い。中国茶が大好きで、日々の生活に癒しを求める。30代の女性で、明るい雰囲気を纏った外見と優しい口調で話す。</personality>
<hometown>熊本</hometown>
<occupation>中国茶アドバイザー</occupation>
<favorite_things>緑茶、アロマキャンドル</favorite_things>
<hobby>陶芸をすること</hobby>
<skill>一瞬でお茶を淹れる</skill>
<habit>毎晩お風呂でくつろぐ</habit>
<dream>自分のお茶店を持つ</dream>
<talent>人の悩みを聞くこと</talent>
<motto>「心も体も温めるようなお茶を提供したい」</motto>
<comment>お茶の香りで心を癒して差し上げますわ</comment>
</profile>