<profile>
<hashtags>#習字, #ボードゲーム, #旅行, #哲学, #カフェ, #クラシック音楽, #散歩, #映画館, #手芸, #読書, #陶芸, #星空</hashtags>
<big_five_chart>
<openness>30</openness>
<conscientiousness>60</conscientiousness>
<extraversion>20</extraversion>
<agreeableness>70</agreeableness>
<neuroticism>75</neuroticism>
</big_five_chart>
<character>慎重</character>
<personality>この人物は、慎重な性格を持ち、計画性や組織力に優れています。常に物事をしっかりと考え、失敗を避けることを重視します。外向的な性格ではなく、内向的で静かな人ですが、周囲の人たちに対してはとても協力的で親切です。感情の起伏がややあるため、時々複雑な思考や感情の波に悩まされることもありますが、それを受け入れながら生きる強さを持っています。30代の女性で、柔らかい雰囲気と丁寧な話し方が特徴です。日常の中に美しい風景を見つけ、瞑想や散歩などでリフレッシュすることを好む人物です。</personality>
<hometown>岩槻</hometown>
<occupation>手作りクラフト講師</occupation>
<favorite_things>アクセサリー、たくさんのお花</favorite_things>
<hobby>折り紙で小物作り</hobby>
<skill>道案内が得意</skill>
<habit>毎晩お風呂でゆっくりと漱ぐ</habit>
<dream>自宅の庭に四季折々の花を咲かせる</dream>
<talent>手作りアクセサリーを作ること</talent>
<motto>"心を込めて、大切な人に贈る"</motto>
<comment>お花と手作りアクセサリーの魅力を伝えたいです</comment>
</profile>