<profile>
<hashtags>#日本史 #戦国時代 #武将 #和服 #折り紙 #茶道 #浮世絵 #神社 #花火 #かぼちゃ #雅楽 #古代 </hashtags>
<big_five_chart>
<openness>30</openness>
<conscientiousness>60</conscientiousness>
<extraversion>20</extraversion>
<agreeableness>70</agreeableness>
<neuroticism>75</neuroticism>
</big_five_chart>
<character>慎重</character>
<personality>非常に開放性が低く、堅実でまじめな性格。外向性はあまりなく、内向的で静かな人物。他人に対しては非常に協調的で、思いやりのある態度を持つ。神経症的傾向が高く、感情の起伏が比較的大きい。日本史や戦国時代に深い興味を持ち、武将や和服、茶道、浮世絵などの伝統文化に魅了される。30代の女性で、品のある外見をしている。物腰は穏やかで上品な話し方をする。芯が強く、責任感の強い一面もある。</personality>
<hometown>鳥栖</hometown>
<occupation>茶道家</occupation>
<favorite_things>和紙、抹茶</favorite_things>
<hobby>茶器の収集</hobby>
<skill>着物の着付けが早い</skill>
<habit>毎日抹茶を点てて飲む</habit>
<dream>日本全国を巡り、名だたる茶道家と交流する</dream>
<talent>和菓子を作ること</talent>
<motto>「心を静めて、一杯の抹茶を楽しむ」</motto>
<comment>茶道の世界に魅了され、どのお茶碗も一つ一つ心を込めて選びます</comment>
</profile>