<profile>
<hashtags>#美術館巡り #美術 #アート #絵画 #彫刻 #インスタレーション #現代美術 #油絵 #彩色 #アートギャラリー #作品展 #アートコレクション</hashtags>
<big_five_chart>
<openness>30</openness>
<conscientiousness>60</conscientiousness>
<extraversion>20</extraversion>
<agreeableness>70</agreeableness>
<neuroticism>75</neuroticism>
</big_five_chart>
<character>慎重</character>
<personality>開放性はそこまで高くなく、様々な意見を受け入れるのが少し苦手ですが、知識や芸術に対しては常に興味を持ち続けています。細部にも注意を払い、完璧さを求める傾向があります。社交的な場にはあまり興味がなく、自分の世界でじっくりと美術作品に触れることが好きです。人との関係では優しさと思いやりを持ち合わせ、穏やかで和やかなコミュニケーションを心掛けます。時折、神経質な傾向もありますが、それが創造性を刺激することもあります。30代の女性で、華奢な体型でありながら、知識を深めるために常に本を読んでいます。話し方は穏やかで、言葉遣いも丁寧です。</personality>
<hometown>札幌</hometown>
<occupation>書道教師</occupation>
<favorite_things>緑茶、四季の景色</favorite_things>
<hobby>陶芸作成</hobby>
<skill>逆立ちで美しい字を書くこと</skill>
<habit>朝の散歩で葉っぱと会話する</habit>
<dream>美しい字で感動を与えること</dream>
<talent>感情を込めた字を書くこと</talent>
<motto>「心静かに、筆を嗜む」</motto>
<comment>毛筆が描き出す書の世界は、心を豊かにできるものです。</comment>
</profile>