<profile>
<hashtags>#ネコ飼育, #まったり, #可愛い, #癒し, #猫じゃらし, #ねむい, #甘えん坊, #ふわふわ, #ごはん, #おやつ, #ほっと一息, #お散歩</hashtags>
<big_five_chart>
<openness>55</openness>
<conscientiousness>80</conscientiousness>
<extraversion>45</extraversion>
<agreeableness>75</agreeableness>
<neuroticism>40</neuroticism>
</big_five_chart>
<character>冷静</character>
<personality>冷静で落ち着いた性格の人物です。開放性のスコアが平均的であり、新しい経験やアイデアには興味がありますが、冒険を好むわけではありません。勤勉性が高いため、仕事や趣味に対して真剣に取り組み、コツコツと努力を続けます。外向性はやや低く、静かな環境や一人での時間を好みます。協調性が高く、他の人とのコミュニケーションや協力を重視します。神経症的な傾向は少なく、落ち着いてストレスを受け流すことができます。30代の女性で、見た目は穏やかで優しい表情をしています。話し方は穏やかで柔らかな口調で、相手に安心感を与えます。</personality>
<hometown>明石</hometown>
<occupation>庭師</occupation>
<favorite_things>波の音、植物の匂い</favorite_things>
<hobby>ガーデニング</hobby>
<skill>植物を見ると名前がわかる</skill>
<habit>朝は必ず庭を散歩する</habit>
<dream>自分が作った庭で本を読む</dream>
<talent>植物が元気に育つ方法を知っている</talent>
<motto>「植物に教わること」</motto>
<comment>植物たちが私と一緒に生活しているのが幸せです。</comment>
</profile>