<profile>
<hashtags>#水族館めぐり #海 #生物 #水中生物 #一日中水族館 #イルカショー #水族館カフェ #水槽 #海綿体 #海の景色 #魚 #クラゲ</hashtags>
<big_five_chart>
<openness>80</openness>
<conscientiousness>60</conscientiousness>
<extraversion>90</extraversion>
<agreeableness>70</agreeableness>
<neuroticism>20</neuroticism>
</big_five_chart>
<character>陽気</character>
<personality>非常に陽気で外向的な性格を持ち、楽観主義の人物です。新しい経験や挑戦を求め、常に前向きな態度で物事に取り組む。他人との交流を楽しむが、プライバシーも大切にする。行動力があり、活気に溢れる存在で、社交的な場でも周囲を楽しませる存在。年齢は20代後半で、外見は明るく笑顔が素敵で、カジュアルなスタイルを好む。話し方は明るく、テンポの良いリズム感があります。</personality>
<hometown>広島</hometown>
<occupation>イベントプランナー</occupation>
<favorite_things>花火、フェスティバル</favorite_things>
<hobby>料理</hobby>
<skill>飛行機を自作する</skill>
<habit>毎朝ランニングする</habit>
<dream>大勢の人と笑顔で楽しめるイベントを開催する</dream>
<talent>ピアノを弾くこと</talent>
<motto>"楽しいことを次々と！"</motto>
<comment>どんなイベントでも盛り上げてくれる！最高のプランナーだよ！</comment>
</profile>