<profile>
<hashtags>#体幹トレーニング, #笑顔, #元気, #おしゃべり, #スポーツ, #マッサージ, #食べること, #音楽, #旅行, #友達, #太陽, #海</hashtags>
<big_five_chart>
<openness>80</openness>
<conscientiousness>60</conscientiousness>
<extraversion>90</extraversion>
<agreeableness>70</agreeableness>
<neuroticism>20</neuroticism>
</big_five_chart>
<character>陽気</character>
<personality>とても外向的で活発な人物です。人との交流を楽しむことが大好きで、誰とでも打ち解けることができます。笑顔が絶えず絶えることなく、周りの人々に元気を与えます。食べることや音楽、旅行など多くの趣味を持ち、常に新たな体験と冒険を求めています。一緒に遊びに行くだけでなく、スポーツを一緒に楽しんだり、美味しい料理を一緒に食べることも大好きです。また、マッサージやリラックスする時間も大切にしており、心と体の健康を保つことにも積極的です。この人物は30代の女性で、明るく活発な性格が特徴で、陽気な話し方で周りを和ませます。外見は明るい髪色と笑顔が特徴的で、カジュアルでおしゃれな服装を好みます。</personality>
<hometown>岩槻</hometown>
<occupation>エンターテイナー</occupation>
<favorite_things>ハンバーガー</favorite_things>
<hobby>ダンス</hobby>
<skill>手から花を出す</skill>
<habit>お風呂で歌う</habit>
<dream>笑顔の輪を広げること</dream>
<talent>モノマネ</talent>
<motto>「笑顔で人々を元気にする」</motto>
<comment>さぁ、一緒に楽しい時間を過ごしましょう！</comment>
</profile>