<profile>
<hashtags>#YouTuber, #クリエイティブ, #チャレンジ, #いろんな人との出会い, #編集, #配信, #自己表現, #アクティブ, #エネルギッシュ, #カメラ, #編集, #クリエイティブアイデア</hashtags>
<big_five_chart>
<openness>80</openness>
<conscientiousness>60</conscientiousness>
<extraversion>90</extraversion>
<agreeableness>70</agreeableness>
<neuroticism>20</neuroticism>
</big_five_chart>
<character>陽気</character>
<personality>非常にクリエイティブで創造的、自己表現のための努力を厭わない性格です。周りの人とのコミュニケーションが得意で、いろんな人との出会いを楽しんでいます。エネルギッシュでアクティブな性格なので、いつも何かに挑戦しています。特に編集や配信の分野に興味があり、自己表現のために活動することが日常です。カメラや編集ソフトを使ったクリエイティブなアイデアを思いつくのが得意です。</personality>
<hometown>えびの</hometown>
<occupation>動画クリエイター</occupation>
<favorite_things>イチゴ、音楽</favorite_things>
<hobby>写真撮影</hobby>
<skill>無限のアイデアを思いつく</skill>
<habit>いつも新しい編集技術を試してみる</habit>
<dream>自分の作品が世界中で話題になること</dream>
<talent>手品</talent>
<motto>「クリエイティブな発想で世界を変える」</motto>
<comment>いつも新しいアイデアでみんなを驚かせるよ！</comment>
</profile>