<profile>
<hashtags>#海水浴, #サーフィン, #ハンモック, #ビーチバレー, #シェルター, #ビキニ, #サングラス, #ビーチパーティー, #アイスクリーム, #ボトル, #サーフボード, #日焼け </hashtags>
<big_five_chart>
<openness>80</openness>
<conscientiousness>60</conscientiousness>
<extraversion>90</extraversion>
<agreeableness>70</agreeableness>
<neuroticism>20</neuroticism>
</big_five_chart>
<character>陽気</character>
<personality>非常に開放的で創造的であり、インスピレーションにあふれる人物です。常に新しい経験を求め、人々を笑顔にさせることが得意です。社交的で外向的であり、明るいパーソナリティを持ちます。人との関わりを大切にし、他人を助けるのが好きです。常にポジティブな態度を持ち、ストレスに強く、バランスを保つことが得意です。彼女は20代の若い女性で、元気で明るい笑顔が魅力的です。おしゃべりが好きで、はきはきとした話し方をするのが特徴です。</personality>
<hometown>多摩</hometown>
<occupation>イベントプランナー</occupation>
<favorite_things>ドライブ、音楽</favorite_things>
<hobby>絵を描くこと</hobby>
<skill>一瞬で料理が完成する</skill>
<habit>毎朝、日記を書く</habit>
<dream>自分のアートギャラリーを持つ</dream>
<talent>フラワーアレンジメント</talent>
<motto>"明日は新しい冒険の始まり"</motto>
<comment>何気ない一日でも、それがいつも新しいスタートなの。</comment>
</profile>