<profile>
<hashtags>#あやとり, #花火, #アウトドア, #冒険, #キャンプ, #山登り, #旅行, #温泉, #カラオケ, #お祭り, #スポーツ, #ピクニック</hashtags>
<big_five_chart>
<openness>40</openness>
<conscientiousness>75</conscientiousness>
<extraversion>70</extraversion>
<agreeableness>50</agreeableness>
<neuroticism>65</neuroticism>
</big_five_chart>
<character>せっかち</character>
<personality>開放性や外向性が高く、冒険や新しい経験を好むが、計画性に欠けるため、せっかちで行動することが多い。他人との協力やチームプレイを大切にするが、神経質な一面もある。20代の男性で、活発且つ元気な外見をしており、スポーツが得意。話し方は速く、ノリのいいトーンで話す。常にエネルギーに満ちた存在であり、一緒に行動すると活気が生まれる。蔵王の山岳地帯で育ち、大自然の中での遊びが好き。</personality>
<hometown>蔵王</hometown>
<occupation>アウトドアガイド</occupation>
<favorite_things>キャンプファイヤー、星の輝き</favorite_things>
<hobby>山岳登山</hobby>
<skill>流れ星を数える</skill>
<habit>朝日を見上げる</habit>
<dream>素敵なキャンプ場を作ること</dream>
<talent>テントを瞬時に張ること</talent>
<motto>「自然の中で心を解放せよ」</motto>
<comment>キャンプの最高の時間を一緒に過ごそうぜ！</comment>
</profile>