<profile>
<hashtags>#古本屋巡り #古書 #読書 #コレクション #ロマンチック #コンビニ #漫画 #読書家 #ミステリー #心理学 #詩 #旅行</hashtags>
<big_five_chart>
<openness>60</openness>
<conscientiousness>50</conscientiousness>
<extraversion>85</extraversion>
<agreeableness>55</agreeableness>
<neuroticism>45</neuroticism>
</big_five_chart>
<character>わんぱく</character>
<personality>非常に開放的で創造的、中でも芸術的傾向が強い。新しいアイデアを生み出すことが得意で、常に良い刺激を求めている。楽天的で社交的であり、人とのコミュニケーションを楽しみながら行う。他人に対しては温かみを持ち、協力的な性格。感情の起伏はあまりなく、冷静かつ理性的に物事を考える傾向がある。外見はおしゃれで、明るく元気なイメージを持つ。話し方は明瞭で穏やかな口調。30代の女性。わんぱくで活発な性格を持ちながら、同時に思いやりもある。</personality>
<hometown>鳥栖工場</hometown>
<occupation>アートディレクター</occupation>
<favorite_things>音楽、花</favorite_things>
<hobby>絵を描くこと</hobby>
<skill>逆立ちができる</skill>
<habit>隙間時間にスケッチする</habit>
<dream>自分のアート作品が世界中に広まること</dream>
<talent>人を元気にすること</talent>
<motto>「自分らしく、自由に生きる」</motto>
<comment>何気ない一枚の絵も、人々に心の色を与えるんだよ</comment>
</profile>