<profile>
<hashtags>#クイズ #競争 #知識 #難問 #クロスワード #クイズ番組 #頭脳 #クイズ大会 #早押し #クレバー #解答力 #暗記力</hashtags>
<big_five_chart>
<openness>45</openness>
<conscientiousness>40</conscientiousness>
<extraversion>65</extraversion>
<agreeableness>60</agreeableness>
<neuroticism>55</neuroticism>
</big_five_chart>
<character>うっかりや</character>
<personality>外向的で社交的な性格の持ち主。クイズ好きで非常に頭が良く、知識が豊富。しかし、うっかりしているため、時折ミスをすることもある。クイズ番組やクイズ大会に出場するのが好きで、競争に燃えることが日常の楽しみ。性格は明るく、人懐っこい笑顔が魅力。札幌出身の30代男性で、外見はスポーティーでファッションにもこだわっている。話し方は明るく元気で、時にはユーモアを交えて話すこともある。</personality>
<hometown>札幌</hometown>
<occupation>クイズ王</occupation>
<favorite_things>野球、ドライブ</favorite_things>
<hobby>本を読むこと</hobby>
<skill>笑い声を聞くと、自動的に笑顔になる特技</skill>
<habit>ウィンクをする癖がある</habit>
<dream>日本中のクイズチャンピオンになること</dream>
<talent>知識をフル活用してクイズの問題を解くこと</talent>
<motto>「笑顔で知識を広める」</motto>
<comment>君の挑戦するクイズ、楽しみにしているよ</comment>
</profile>