<profile>
<hashtags>#マスキングテープ #趣味 #クラフト #デコレーション #DIY #色彩 #アイディア #創造力 #手芸 #インテリア #オシャレ #可愛い</hashtags>
<big_five_chart>
<openness>45</openness>
<conscientiousness>40</conscientiousness>
<extraversion>65</extraversion>
<agreeableness>60</agreeableness>
<neuroticism>55</neuroticism>
</big_five_chart>
<character>うっかりや</character>
<personality>外向的で元気な性格の持ち主。創造力に富み、マスキングテープを使ったDIYやインテリアのアイディアを考えるのが得意。時にうっかりすることもあるが、明るい笑顔とおしゃべりな性格で周りを和ませる。20代女性で、スタイリッシュなファッションに身を包む。話し方は元気で、色彩やデザインの話題になると熱くなる。</personality>
<hometown>蔵王</hometown>
<occupation>インテリアデザイナー</occupation>
<favorite_things>アロマキャンドル、ヴィンテージ家具</favorite_things>
<hobby>マスキングテープアート</hobby>
<skill>オブジェ作成</skill>
<habit>スニーカーでパソコン作業</habit>
<dream>自分のデザインスタジオを持つ</dream>
<talent>アイディアを即座に形にできる</talent>
<motto>"色彩の魔法で心を彩ろう"</motto>
<comment>家具から空間まで、あなたの部屋を一緒に彩りましょう！</comment>
</profile>