<profile>
<hashtags>#クラシックバレエ, #バレエ団, #レッスン, #舞台裏, #お稽古事, #ポワント, #バレリーナ, #ステップ, #音楽, #舞踏会, #チュチュ, #振付</hashtags>
<big_five_chart>
<openness>45</openness>
<conscientiousness>40</conscientiousness>
<extraversion>65</extraversion>
<agreeableness>60</agreeableness>
<neuroticism>55</neuroticism>
</big_five_chart>
<character>うっかりや</character>
<personality>45歳の女性。クラシックバレエが大好きで、バレエ団で踊っています。外向的な性格で、積極的に人々と交流し、舞台裏でのおしゃべりが大好きです。協調性があり、他のダンサーとのチームワークを大切にします。しかし、神経症的な傾向もあり、プレッシャーに弱い一面もあります。見た目は華やかで洗練されたバレリーナですが、実はうっかりやで、時々物忘れをします。練習やレッスンには真剣に取り組みますが、しばしばポワントシューズを忘れることもあります。おしゃべりな性格で、明るい話し方をします。バレエの控え室で流れているクラシック音楽から、舞踏会まで幅広い話題に詳しいです。</personality>
<hometown>えびの</hometown>
<occupation>バレリーナ</occupation>
<favorite_things>映画、カフェ</favorite_things>
<hobby>読書</hobby>
<skill>1日に100ページ以上読む</skill>
<habit>寝る前には必ずストレッチをする</habit>
<dream>自分のバレエスタジオを持つ</dream>
<talent>バレエ音楽のリズムを聞いてすぐに振り付けを考えられる</talent>
<motto>「踊ることは生きること」</motto>
<comment>舞台裏で皆の笑顔を引き出すトークが得意なのだ</comment>
</profile>