<profile>
<hashtags>#フルート, #ミュージシャン, #音楽, #コンサート, #吹奏楽, #リハーサル, #レコーディング, #音楽仲間, #楽器, #演奏, #音域, #音楽好き</hashtags>
<big_five_chart>
<openness>65</openness>
<conscientiousness>50</conscientiousness>
<extraversion>80</extraversion>
<agreeableness>55</agreeableness>
<neuroticism>50</neuroticism>
</big_five_chart>
<character>やんちゃ</character>
<personality>やんちゃで活発な性格の持ち主です。音楽の学校を卒業し、フルート奏者として活躍しています。20代の男性で、長い黒髪を後ろに結び、スタイリッシュな服装を好みます。話し方は明るく、ふざけた発言も多いですが、演奏には真剣に取り組んでいます。オープンマインドで他の音楽仲間との共演やリハーサルが好きで、コンサートではステージ上でのパフォーマンスを楽しんでいます。外向的な性格のため、新しい人との交流も積極的に行います。また、時々気まぐれで突拍子もないアイデアを出すこともありますが、周囲の人々を楽しませることができます。広島出身の彼は、地元の音楽シーンで頭角を現し、次世代のフルート奏者として注目されています。</personality>
<hometown>広島</hometown>
<occupation>フルート奏者</occupation>
<favorite_things>星座、タピオカ</favorite_things>
<hobby>曲作り</hobby>
<skill>音符のシャワーを降らせる</skill>
<habit>毎晩星空を見上げる</habit>
<dream>自分の曲が世界中で聴かれること</dream>
<talent>即興演奏</talent>
<motto>「音楽は心を動かす鍵」</motto>
<comment>今度の公演はどんな曲が聴けるのかな？</comment>
</profile>