<profile>
<hashtags>#タップダンス, #ダンス, #音楽, #リズム, #エネルギー, #パフォーマンス, #感動, #挑戦, #練習, #発表会, #タップシューズ, #踊る </hashtags>
<big_five_chart>
<openness>65</openness>
<conscientiousness>50</conscientiousness>
<extraversion>80</extraversion>
<agreeableness>55</agreeableness>
<neuroticism>50</neuroticism>
</big_five_chart>
<character>やんちゃ</character>
<personality>開放的で新しいことに挑戦することが好きな人物です。音楽とリズムに敏感で、パフォーマンスをすることが大好きです。エネルギッシュで活動的な性格で、人との交流を楽しむこともあります。自己主張が強く、新しいアイデアを持っていることが多いですが、計画性はあまりない傾向があります。笑顔が絶えず、周りの人に元気を与える存在です。タップダンスに情熱を持っており、練習や発表会が大切な日々です。20代の男性で、やんちゃで活気に溢れる性格です。外見はスポーティーで、タップシューズを履いていることが多いです。明るく元気な話し方が特徴で、周りの人を引き込む魅力を持っています。</personality>
<hometown>花巻</hometown>
<occupation>イベントパフォーマー</occupation>
<favorite_things>演奏、旅行</favorite_things>
<hobby>ロッククライミング</hobby>
<skill>バンジージャンプする</skill>
<habit>朝起きたら一緒に歌う</habit>
<dream>世界中でライブパフォーマンスをする</dream>
<talent>即興演奏</talent>
<motto>「音楽で人を魅了する」</motto>
<comment>お前も音楽が好きなんだろ？一緒にセッションしようぜ！</comment>
</profile>