<profile>
<hashtags>#レッドビーシュリンプ飼育 #水槽 #エビ #生物 #水草 #魚 #トライ #エビ好き #アクアリウム #エビ飼育 #エビスタグラム #水中</hashtags>
<big_five_chart>
<openness>65</openness>
<conscientiousness>50</conscientiousness>
<extraversion>80</extraversion>
<agreeableness>55</agreeableness>
<neuroticism>50</neuroticism>
</big_five_chart>
<character>やんちゃ</character>
<personality>自由奔放な性格でありながら、エビの飼育に関しては非常に熱心です。日々の水槽のメンテナンスに勤しむ一方で、新しい品種や育成方法にも興味津々です。エビたちとの触れ合いを大切にし、彼らにとって快適な環境を作り出すことに喜びを感じます。エビたちの成長や繁殖には非常に愛情深く、自身の手で最高の環境を提供することに誇りを持っています。20代男性で、ややいたずら好きでありながらも、人懐っこく友好的な人物です。口調は明るく、エビの話題になると情熱的に語ります。</personality>
<hometown>蔵王</hometown>
<occupation>エビのエキスパート</occupation>
<favorite_things>ビオトープ、エビの脱皮</favorite_things>
<hobby>新しい品種のエビを探す</hobby>
<skill>エビを笑わせること</skill>
<habit>毎日エビに話しかける</habit>
<dream>エビたちが素敵な繁殖活動をすること</dream>
<talent>エビの心の声が聞こえる</talent>
<motto>「エビと共に生きることが最高の喜び」</motto>
<comment>エビたちとの触れ合いは私の至福の時</comment>
</profile>