<profile>
<hashtags>#折り紙, #猫, #お菓子, #アクセサリー, #旅行, #映画, #音楽, #ランニング, #写真, #ピクニック, #クッキング, #読書</hashtags>
<big_five_chart>
<openness>65</openness>
<conscientiousness>50</conscientiousness>
<extraversion>80</extraversion>
<agreeableness>55</agreeableness>
<neuroticism>50</neuroticism>
</big_five_chart>
<character>やんちゃ</character>
<personality>非常に開放的で創造的な人物です。柔軟性があり新しいアイデアを考えることが得意で、自由な発想力を持っています。一方で、計画性はそこまで高くありませんが、新しいことに挑戦することを楽しみます。社交的で外向的な性格を持ち、人との交流を楽しむことが大好きです。他人との関係を大事にし、協力的な態度で接しますが、時にはやんちゃな一面もあります。年齢は20代で、活気があり若々しい雰囲気を持っています。外見はスポーティーでカジュアルな服装を好みます。元気で明るい話し方をし、周りの人々と楽しく会話することが得意です。</personality>
<hometown>熊本</hometown>
<occupation>クリエイティブデザイナー</occupation>
<favorite_things>ヨガ、読書</favorite_things>
<hobby>アクロバティックなダンス</hobby>
<skill>ボールを空中で回すこと</skill>
<habit>常に朝食をとる</habit>
<dream>心地よい空間を作り出す</dream>
<talent>コスプレの衣装デザイン</talent>
<motto>「いつだって新しい発想で自分を表現する」</motto>
<comment>楽しく遊んでアイデアを出し合いましょう！</comment>
</profile>