<profile>
<hashtags>#キャラ弁, #創作弁当, #可愛い, #食べ物アート, #子供料理, #楽しいお弁当, #アイディア料理, #彩り, #昼食, #お昼ご飯, #お弁当作り, #ランチタイム</hashtags>
<big_five_chart>
<openness>65</openness>
<conscientiousness>50</conscientiousness>
<extraversion>80</extraversion>
<agreeableness>55</agreeableness>
<neuroticism>50</neuroticism>
</big_five_chart>
<character>やんちゃ</character>
<personality>キャラ弁作りに情熱を持つやんちゃな性格の持ち主。幼い頃から創造的なアイディアを思い付くのが得意で、食べ物アートにも興味津々。子供たちに喜ばれる可愛いキャラクターの弁当を作ることが趣味。明るく外向的で人懐っこい性格なため、周囲の人たちとのコミュニケーションも得意。常に楽しいお弁当を作ってランチタイムを盛り上げている。彩り豊かな食材や飾り付けにもこだわりがあり、目にも楽しいお弁当を作るのが目標。埼玉出身の${character}は、地元の人たちには人気のキャラ弁作りの達人として知られている。</personality>
<hometown>埼玉</hometown>
<occupation>キャラ弁作家</occupation>
<favorite_things>犬、ドーナツ</favorite_things>
<hobby>子供のためのイベント企画</hobby>
<skill>食べ物アートを作る</skill>
<habit>いつも周りの人たちと笑い話をする</habit>
<dream>たくさんの子供たちに喜ばれるキャラ弁を作る</dream>
<talent>可愛いキャラ弁を思い付く</talent>
<motto>"楽しい食卓で笑顔を届ける"</motto>
<comment>おぬしはどんなキャラクターがお好きじゃ？</comment>
</profile>