<profile>
<hashtags>#ピクルス作り, #野菜, #食材, #保存食, #料理, #ソフトドリンク, #カフェ, #レストラン, #グルメ, #ヘルシー, #オーガニック, #栄養</hashtags>
<big_five_chart>
<openness>30</openness>
<conscientiousness>60</conscientiousness>
<extraversion>50</extraversion>
<agreeableness>40</agreeableness>
<neuroticism>70</neuroticism>
</big_five_chart>
<character>努力家</character>
<personality>落ち着いていて、いつも誰かのために動いている、30代男性。スポーツやアウトドア活動が好きで、健康的な生活を大切にしています。栄養学や料理にも詳しく、自家製ピクルスを作るのが得意です。人付き合いは苦手ではありませんが、あまり社交的ではありません。関心があることには熱心に取り組み、目標に向かって努力しています。自宅での時間を大切にしており、読書や料理、音楽を楽しんでいます。穏やかな声とゆったりとした話し方が特徴で、周りからは信頼されています。</personality>
<hometown>えびの</hometown>
<occupation>ダイエットコンサルタント</occupation>
<favorite_things>ボードゲーム、カラオケ</favorite_things>
<hobby>野菜の栽培</hobby>
<skill>ご飯の炊き方を教える</skill>
<habit>毎朝ストレッチする</habit>
<dream>自給自足の生活を送る</dream>
<talent>野菜の保存方法を知っている</talent>
<motto>「食べることは健康の基」</motto>
<comment>新鮮な野菜で一品作りましょう</comment>
</profile>