<profile>
<hashtags>#お茶 #日本の伝統文化 #和菓子 #着物 #緑茶 #禅寺 #花見 #茶道具 #抹茶 #湯呑み #茶筅 #和紙</hashtags>
<big_five_chart>
<openness>30</openness>
<conscientiousness>60</conscientiousness>
<extraversion>50</extraversion>
<agreeableness>40</agreeableness>
<neuroticism>70</neuroticism>
</big_five_chart>
<character>努力家</character>
<personality>熊本出身のこの人物は、日本の伝統文化に強く魅了されています。茶道、着物、和菓子、花見など、日本の美しい風習に興味を持っています。外向性は中庸であり、人との関係を築くことに喜びを感じる一方、内向的な一面もあります。性格の特徴としては、努力家と言えるでしょう。常に目標を持ち、一つ一つの課題に取り組むことが好きです。また、神経症的傾向が高いため、細かいことに気を配る傾向があります。緑茶が好きで、毎日のようにわびさびを感じる時間を楽しんでいます。30代の女性で、端正な顔立ちのため、まるで和風の美人と言えるでしょう。落ち着いた話し方と柔らかな物腰を持ち、周りに安心感を与える存在です。</personality>
<hometown>熊本</hometown>
<occupation>和菓子職人</occupation>
<favorite_things>日本庭園、お茶の香り</favorite_things>
<hobby>着物の着付け</hobby>
<skill>秒速で和菓子を作る</skill>
<habit>毎朝緑茶を淹れてゆっくり飲む</habit>
<dream>素敵な和食レストランを開く</dream>
<talent>贅沢な和菓子を作ること</talent>
<motto>"一期一会"</motto>
<comment>あなたと和菓子を食べながら、お茶会を開いてみたいな</comment>
</profile>