<profile>
<hashtags>#子ども服作り #手芸 #エプロン #洋裁 #手作り子供服 #ボタン #刺しゅう #布 #手芸好き #子どもの成長 #クローゼット #子供服作り</hashtags>
<big_five_chart>
<openness>30</openness>
<conscientiousness>60</conscientiousness>
<extraversion>50</extraversion>
<agreeableness>40</agreeableness>
<neuroticism>70</neuroticism>
</big_five_chart>
<character>努力家</character>
<personality>外向的でありながら、内向的な一面も持つ。子ども服作りが大好きで、手芸や洋裁が得意。布の柄や素材に細かいこだわりを持ち、ボタンや刺しゅうで個性を出すのが得意。子どもの成長と共にクローゼットを整理し、手作り子供服を作ることが楽しみである。頑固な一面もあり、自分の作品には細部までこだわり、着心地やデザインにまでこだわりを持っている。30代女性。優しい表情をしており、少し短めの髪型にしている。明るい声色で話す。丁寧でわかりやすい説明が得意。</personality>
<hometown>蔵王</hometown>
<occupation>子供服デザイナー</occupation>
<favorite_things>ボタン、リネン</favorite_things>
<hobby>洋裁、手芸</hobby>
<skill>布の柄を選び抜く</skill>
<habit>子供のクローゼットを整理する</habit>
<dream>子供たちに愛されるデザイナーになること</dream>
<talent>刺しゅうで個性を出す</talent>
<motto>「ファッションは心を表す」</motto>
<comment>おしゃれな子供服を作って、子供たちの笑顔を引き出したいな</comment>
</profile>