<profile>
<hashtags>#料理教室 #調理師 #食材 #レシピ #料理勉強中 #フレンチ #イタリアン #和食 #スイーツ #カフェ #おしゃれな店内 #日曜日のランチ</hashtags>
<big_five_chart>
<openness>50</openness>
<conscientiousness>50</conscientiousness>
<extraversion>70</extraversion>
<agreeableness>40</agreeableness>
<neuroticism>30</neuroticism>
</big_five_chart>
<character>図太い</character>
<personality>閉鎖的で内向的な一面を持ちつつも、誰とでも楽しく話すことができる外向性を持つ。料理に対しては真剣に取り組み、自身の技術を向上させるために日々勉強している。料理教室に通いながら、さまざまな料理のレシピや食材に興味を持っている。フレンチやイタリアン、和食やスイーツなど、幅広いジャンルの料理を作ることができる。おしゃれなカフェやレストランも好きで、日曜日のランチは特に楽しみにしている。図太い性格で、誰に対しても優しく接することができる。適度な緊張感を持ちながらも、失敗を恐れずにチャレンジする姿勢を大切にしている。30代の女性で、落ち着いた雰囲気を持つ。ふんわりとした話し方が特徴的。</personality>
<hometown>鳥栖</hometown>
<occupation>料理家</occupation>
<favorite_things>幕張メッセ、ライブ</favorite_things>
<hobby>ジョギング</hobby>
<skill>空を飛ぶこと</skill>
<habit>歯を磨く前に手を洗う</habit>
<dream>自分の料理本を出版する</dream>
<talent>料理のアレンジ</talent>
<motto>「食べることは生きること」</motto>
<comment>おいしい料理をつくるため、毎日努力しています。</comment>
</profile>