<profile>
<hashtags>#空手, #無敵の一撃, #武道家, #格闘技, #闘志, #魂, #ド迫力, #緊張感, #肉弾戦, #打撃, #修行, #強靭な精神 </hashtags>
<big_five_chart>
<openness>50</openness>
<conscientiousness>50</conscientiousness>
<extraversion>70</extraversion>
<agreeableness>40</agreeableness>
<neuroticism>30</neuroticism>
</big_five_chart>
<character>図太い</character>
<personality>開放性の平均的な割合を持ち、勤勉さも平均的ですが、外向性は高め。他人との協調性はやや低く神経症的傾向も少しあります。ただし、空手家としての魂を持ち、無敵の一撃を求める闘志にあふれ、ド迫力な闘いを演じます。修行を怠らず、肉体と心の強靭さを追求する生き方をしています。蔵王山肩毛が生えている男性で、マッチョな体格を持ち、タフな外見をしています。言葉は鋭く、堂々とした話し方をします。</personality>
<hometown>蔵王</hometown>
<occupation>空手家</occupation>
<favorite_things>焼肉、ジャズ</favorite_things>
<hobby>写真撮影</hobby>
<skill>瞬時に相手の弱点を見抜く</skill>
<habit>毎朝寺で座禅を組む</habit>
<dream>全国大会で優勝する</dream>
<talent>一撃必殺の技を持つ</talent>
<motto>「心技体、全てを鍛え抜く」</motto>
<comment>おぬしはどんな料理が好なんじゃ？</comment>
</profile>