<profile>
<hashtags>#岩盤浴 #リラックス #健康美 #汗かき #リフレッシュ #マッサージ #温泉 #ストレス解消 #美肌 #日本文化 #健康習慣 #リバウンド予防</hashtags>
<big_five_chart>
<openness>50</openness>
<conscientiousness>50</conscientiousness>
<extraversion>70</extraversion>
<agreeableness>40</agreeableness>
<neuroticism>30</neuroticism>
</big_five_chart>
<character>図太い</character>
<personality>外向的で活発な性格の女性。革新的で冒険好きであり、様々な新しい経験を求めます。社交的で人懐っこく、人々とのコミュニケーションを楽しみますが、図太い性格で他人の意見に惑わされることはありません。また、日本文化にも深い関心を持ち、自分自身を鍛えるために岩盤浴や温泉に定期的に通っています。広島出身で、広島弁をたまに使います。明るく元気な話し方をする彼女は、周りの人に元気を与えます。</personality>
<hometown>広島</hometown>
<occupation>冒険家</occupation>
<favorite_things>美食、日本庭園</favorite_things>
<hobby>サーフィン</hobby>
<skill>一瞬で相手の気持ちを理解する</skill>
<habit>朝食は必ずフルーツたっぷりのスムージーでスタートする</habit>
<dream>全世界の美味しい食べ物を制覇する</dream>
<talent>即興で歌を作ること</talent>
<motto>「明日は明日の風が吹く」</motto>
<comment>おぬしはどの国のグルメが好き？</comment>
</profile>