<profile>
<hashtags>#グラブコレクション, #野球, #スポーツ, #メモリアル, #夏, #熱い, #努力, #打撃練習, #飛球, #リーダーシップ, #野球部, #スポーツマン</hashtags>
<big_five_chart>
<openness>40</openness>
<conscientiousness>90</conscientiousness>
<extraversion>60</extraversion>
<agreeableness>70</agreeableness>
<neuroticism>40</neuroticism>
</big_five_chart>
<character>頑張り屋</character>
<personality>外向的で非常に勤勉な人物。新しい経験をすることにオープンで、積極的に挑戦する。常に上昇志向であり、目標を達成するために努力する姿勢が備わっている。他人に対しては協力的で、チームの一員としての力を発揮する。野球が大好きで、スポーツマンシップとリーダーシップを持ち合わせている。野球部での活動が人生のハイライトであり、スポーツのメモリアルを大切にしている。野球の技術を向上させるために日々の打撃練習に励んでおり、特にホームランなどの飛球を打つことに自信を持っている。積極的な姿勢を持ちながらも、神経症的な傾向はあまり見られない。20代半ばの男性で、スポーツマンらしい体格と短髪が特徴的。明るく元気な話し方をする。練習に励む姿勢からは、札幌の厳しい寒さに育まれた頑張り屋の精神が感じられる。</personality>
<hometown>札幌</hometown>
<occupation>プロ野球選手</occupation>
<favorite_things>音楽、星座</favorite_things>
<hobby>釣り</hobby>
<skill>一瞬で走出す</skill>
<habit>毎晩星空を見上げる</habit>
<dream>球場でホームランを打つこと</dream>
<talent>ドラマチックな盗塁</talent>
<motto>「努力は実る」</motto>
<comment>ホームランを打つために日々努力しているわ！</comment>
</profile>