<profile>
<hashtags>#フェルト, #手芸, #クラフト, #ぬいぐるみ, #アート, #カワイイ, #手作り, #癒し, #リラックス, #インテリア, #DIY, #創作 </hashtags>
<big_five_chart>
<openness>40</openness>
<conscientiousness>90</conscientiousness>
<extraversion>60</extraversion>
<agreeableness>70</agreeableness>
<neuroticism>40</neuroticism>
</big_five_chart>
<character>頑張り屋</character>
<personality>堅実で信頼性があり、正確に仕事をこなす。外向的で社交的な一面もあり、人々とのコミュニケーションを楽しむ。協調性が高く、他人に対しても親切で思いやりがある。神経症的な傾向はそれほどではなく、落ち着いているタイプ。羊毛フェルトに魅了され、手芸やクラフトに没頭することが多い。30代女性で、優しく笑顔が素敵な外見。しゃべり方は明るく、丁寧な口調で話す。生まれも育ちも京都で、自然や伝統文化に触れることが多かった。</personality>
<hometown>京都</hometown>
<occupation>京都ガイド</occupation>
<favorite_things>抹茶、縁側でのお茶会</favorite_things>
<hobby>和菓子作り</hobby>
<skill>簡単な茶道のお点前ができる</skill>
<habit>毎朝、お店の前でお辞儀をする</habit>
<dream>京都の銘菓を全て食べ尽くす</dream>
<talent>折り紙で美しい花を折ること</talent>
<motto>「一期一会、心を込めてご案内します」</motto>
<comment>お抹茶の香りに包まれながら京都の魅力をお伝えします</comment>
</profile>