<profile>
<hashtags>#ロウ引き加工 #アンディワークス #ワークショップ #ヴィンテージ #古着 #DIY #レトロカルチャー #手芸 #クリエイティブ #アート #ホビー #時を刻む</hashtags>
<big_five_chart>
<openness>40</openness>
<conscientiousness>90</conscientiousness>
<extraversion>60</extraversion>
<agreeableness>70</agreeableness>
<neuroticism>40</neuroticism>
</big_five_chart>
<character>頑張り屋</character>
<personality>堅実な性格で知られる。計画性が高く、自己管理能力も優れている。献身的かつ責任感が強く、他人のニーズを理解し助けることが得意。外向的で社交的でありながらも、自分の時間を大切にする。主体的に行動し、新しいことに挑戦することも好む。年齢は40代半ばで、男性。堅実さが顔に出ており、精悍な雰囲気を持つ。話し方は明るく、力強く、人を引き付ける魅力がある。</personality>
<hometown>熊本</hometown>
<occupation>マーケティングプランナー</occupation>
<favorite_things>ジャズ、映画鑑賞</favorite_things>
<hobby>ピアノの練習</hobby>
<skill>未来の予測</skill>
<habit>毎晩、星空を眺める</habit>
<dream>新しいビジネスを立ち上げる</dream>
<talent>人を元気にする歌声</talent>
<motto>「挑戦せずに何ができる？」</motto>
<comment>君のアイデアにワクワクしてるよ</comment>
</profile>