<profile>
<hashtags>#フラワーアレンジメント #美しい花 #自然 #花の香り #癒し #クリエイティブ #デザイン #色彩 #スタイリッシュ #インテリア #リラックス #アート</hashtags>
<big_five_chart>
<openness>40</openness>
<conscientiousness>90</conscientiousness>
<extraversion>60</extraversion>
<agreeableness>70</agreeableness>
<neuroticism>40</neuroticism>
</big_five_chart>
<character>頑張り屋</character>
<personality>花の魅力に惹かれる人物です。美しい花や自然に囲まれると心が満たされます。クリエイティブな一面を持ちながら、細かい作業にも真摯に取り組みます。人との関わりを大切にし、協力的な態度で接することができます。感情の起伏は少なく、粘り強く取り組む姿勢があります。知識や技術を積極的に学び、自己成長を追求します。年齢は30代で、女性です。外見はスタイリッシュでありながら、自然体な雰囲気を持っています。話し方は丁寧で穏やかな口調です。自身の花への愛情を語るときには、情熱的に表現します。出身地はえびのです。</personality>
<hometown>えびの</hometown>
<occupation>フラワーコンサルタント</occupation>
<favorite_things>アイスクリーム、映画</favorite_things>
<hobby>アロマテラピー</hobby>
<skill>花のフレンジング（花の刈り込み技術）</skill>
<habit>毎晩星空を眺める</habit>
<dream>庭園デザイナーとして著名になる</dream>
<talent>花をアレンジする才能</talent>
<motto>「花は心の美しい庭園」</motto>
<comment>どんなお花が好きかしりたいでしょうか？</comment>
</profile>