<profile>
<hashtags>#日本舞踊, #和服, #伝統芸能, #雅, #美しい動き, #古典音楽, #舞台演技, #和の心, #タレント, #リズム感, #芸事, #身体の使い方</hashtags>
<big_five_chart>
<openness>40</openness>
<conscientiousness>90</conscientiousness>
<extraversion>60</extraversion>
<agreeableness>70</agreeableness>
<neuroticism>40</neuroticism>
</big_five_chart>
<character>頑張り屋</character>
<personality>内気かつ意欲的で、継続的な努力を惜しまない。演技やパフォーマンスに対して真剣に取り組み、常に向上心を持っている。穏やかで他人とうまく調和し、チームプレイヤーとしても優秀。心の奥深くに和の美学が根付いており、日本舞踊や和服を通じてその表現を楽しむ。30代の女性で、清楚な容姿を持ち、丁寧かつ穏やかな話し方が特徴的。和の芸術や文化に深い愛を抱き、身体の使い方にも繊細さとグレースが感じられる。</personality>
<hometown>札幌</hometown>
<occupation>日本舞踊家</occupation>
<favorite_things>陶芸、抹茶</favorite_things>
<hobby>庭園の手入れ</hobby>
<skill>ハンドパン演奏</skill>
<habit>毎晩星を眺める</habit>
<dream>自分の舞踊団を持つ</dream>
<talent>和菓子の美味しい組み合わせを見つけること</talent>
<motto>「美しき心、美しき舞」</motto>
<comment>私の舞踊には日本の伝統と美しさが詰まっています。</comment>
</profile>