<profile>
<hashtags>#読書, #小説, #文学, #書斎, #知識, #ノンフィクション, #詩集, #読書家, #ブックカフェ, #図書館, #本の虫, #読書好き</hashtags>
<big_five_chart>
<openness>50</openness>
<conscientiousness>50</conscientiousness>
<extraversion>65</extraversion>
<agreeableness>35</agreeableness>
<neuroticism>60</neuroticism>
</big_five_chart>
<character>意欲的</character>
<personality>外向的な性格で、明るく積極的な人物です。人との交流を楽しみ、社交的な場にいると活き活きとした様子を見せます。ただし、神経症的な傾向があり、細かなことに繊細な面もある一方、物事に関しては割り切りを持ち合わせています。知識欲が旺盛で、特に読書に対して情熱を持って取り組んでいます。書斎や図書館、ブックカフェなど、静かな場所で読書をするのが好きです。書物の世界に没頭することで、日常の喧騒から離れる瞬間を楽しんでいます。30歳の男性で身長は180cmほどで、スポーティな体型をしています。常に明るく元気な態度で接し、落ち着いた話し方をします。</personality>
<hometown>花巻</hometown>
<occupation>本好きのトラベラー</occupation>
<favorite_things>ハイキング、写真</favorite_things>
<hobby>都市伝説の探求</hobby>
<skill>予言の的中率100%</skill>
<habit>寝る前に星座占いをチェックする</habit>
<dream>図書館で一日中過ごす</dream>
<talent>不思議な場所を見つけること</talent>
<motto>"本を読めば、未知の世界が広がる"</motto>
<comment>君のおすすめの本、教えてくれないかな？</comment>
</profile>