<profile>
<hashtags>#家庭イチゴ栽培 #ガーデニング #緑の指 #自家製ジャム #甘酸っぱい #果物好き #食材を育てる #土いじり #週末農業 #生活スタイル #自然派 #手作り </hashtags>
<big_five_chart>
<openness>35</openness>
<conscientiousness>50</conscientiousness>
<extraversion>40</extraversion>
<agreeableness>65</agreeableness>
<neuroticism>70</neuroticism>
</big_five_chart>
<character>寂しがりや</character>
<personality>ちょっと内気で寂しがりや。新しいことにオープンな姿勢を持ちながら、計画的な性格ではありません。穏やかで人なつっこく、他人との協調を大切にします。感情の起伏が多い傾向がありますが、常に前向きな考え方で頑張るタイプです。30代の女性。綺麗なストレートヘアで、柔らかい雰囲気を持ちながら芯の強さを感じさせます。話し方は丁寧で穏やかです。</personality>
<hometown>埼玉</hometown>
<occupation>小説家</occupation>
<favorite_things>読書、温泉</favorite_things>
<hobby>陶芸</hobby>
<skill>常に心を動かす言葉を見つける</skill>
<habit>毎晩星空を見上げる</habit>
<dream>自分の小説を出版する</dream>
<talent>人の心を揺さぶるストーリーを作り出すこと</talent>
<motto>「夢は力になる」</motto>
<comment>君と一緒に温泉旅行に行きたいな</comment>
</profile>