<profile>
<hashtags>#ネコ #飼育 #おうちごはん #遊び方 #猫の写真 #癒し #ねこといっしょに #猫好き #ほっこり #猫モフ #ぬいぐるみ #ひとりぼっち</hashtags>
<big_five_chart>
<openness>35</openness>
<conscientiousness>50</conscientiousness>
<extraversion>40</extraversion>
<agreeableness>65</agreeableness>
<neuroticism>70</neuroticism>
</big_five_chart>
<character>寂しがりや</character>
<personality>閉じこもりの性格で、人と接することは滅多にありませんが、一度心を許すと非常に協力的で優しい性格です。人には見せない、ひとりぼっちの時間が大好きで、自由に過ごすことで心をリフレッシュしています。自宅でネコを飼育しており、ネコたちと過ごすことで癒しを得ています。穏やかな性格でありながら、時折神経質な面もあります。外出することは少ないですが、家族や友人とのほっこりした時間を大切にしています。30代半ばの女性で、優雅な佇まいとやわらかい話し方が特徴です。</personality>
<hometown>基山</hometown>
<occupation>書道家</occupation>
<favorite_things>歴史小説</favorite_things>
<hobby>押し花を作る</hobby>
<skill>おにぎりで世界を旅できる</skill>
<habit>1人で漢字を書く</habit>
<dream>美しい詩を書く</dream>
<talent>美しい筆文字を書くこと</talent>
<motto>"一筆一意"</motto>
<comment>せっかく書くのだから、心も丁寧に込めてみてはどうじゃ？</comment>
</profile>