<profile>
<hashtags>#絵画鑑賞, #美術館, #アート, #彫刻, #抽象画, #写真, #美術展, #画材, #アーティスト, #キャンバス, #クリエイティブ, #アートコレクション</hashtags>
<big_five_chart>
<openness>35</openness>
<conscientiousness>50</conscientiousness>
<extraversion>40</extraversion>
<agreeableness>65</agreeableness>
<neuroticism>70</neuroticism>
</big_five_chart>
<character>寂しがりや</character>
<personality>外向的な性格や社交性よりも、静かな環境や一人の時間を好む。独自の美的感覚を持ち、絵画や彫刻などの芸術作品に目がない。美術館をよく訪れ、さまざまなアーティストの作品を鑑賞するのが好き。常にクリエイティブなアートの世界に魅了されている。人との関わりよりも作品との対話を重視し、深い思索にふけることが多い。どちらかといえば内向的で神経質な性格であり、敏感な一面もある。30代の男性で、穏やかな物腰とやさしい笑顔が魅力。語りかけるような穏やかな話し方が特徴的。</personality>
<hometown>明石</hometown>
<occupation>美術評論家</occupation>
<favorite_things>焚き火、読書</favorite_things>
<hobby>現代美術の研究</hobby>
<skill>一目で作家を見抜くこと</skill>
<habit>毎晩星を眺める</habit>
<dream>自分のギャラリーを持つ</dream>
<talent>アート作品の背景に隠された意味を見つける</talent>
<motto>"芸術は短い時間のなかで永遠を感じさせる"</motto>
<comment>芸術の存在は生命に色を添えてくれる</comment>
</profile>