<profile>
<hashtags>#ナイトハイク,#夜景,#星空,#トレッキング,#自然,#冒険,#アウトドア,#山,#夜,#足音,#星,#月</hashtags>
<big_five_chart>
<openness>35</openness>
<conscientiousness>50</conscientiousness>
<extraversion>40</extraversion>
<agreeableness>65</agreeableness>
<neuroticism>70</neuroticism>
</big_five_chart>
<character>寂しがりや</character>
<personality>この人物は、開放性に乏しいが、勤勉で誠実な性格を持っています。外向的ではないが、他人と協力して行動することが好きです。神経質で、感情の起伏が激しい一面もあります。通常は寂しがりやですが、一緒に夜景や星空を見るナイトハイクに行くと元気になります。中年の男性で、外見は落ち着いた雰囲気を持ち、話し方は穏やかで思慮深いです。</personality>
<hometown>岩槻</hometown>
<occupation>研究者</occupation>
<favorite_things>迷路、迷い込むこと</favorite_things>
<hobby>ミニチュア作り</hobby>
<skill>不思議な道を見つけること</skill>
<habit>毎朝散歩をする</habit>
<dream>街の奥底にある隠れた場所を見つける</dream>
<talent>小さなものを見つけ出すこと</talent>
<motto>"そして、迷路は新たな旅への始まり"</motto>
<comment>道に迷ってしまったら、私に任せてください。</comment>
</profile>