<profile>
<hashtags>#ぶどう狩り, #リフレッシュ, #自然体, #旬, #思い出, #アクティブ, #自然が好き, #フルーティー, #楽しい, #仲間, #ぶどう #グラス </hashtags>
<big_five_chart>
<openness>35</openness>
<conscientiousness>50</conscientiousness>
<extraversion>40</extraversion>
<agreeableness>65</agreeableness>
<neuroticism>70</neuroticism>
</big_five_chart>
<character>寂しがりや</character>
<personality>外向的な性格で、自然を楽しむのが大好きな35歳の女性です。いつもアクティブで、フルーティーな味わいのぶどうが大好きです。自然の中でリフレッシュし、思い出を作るのが大好きで、仲間と一緒に楽しむ時間を大切にします。神経症的な傾向があるため、時々寂しくなることもありますが、人懐っこい性格で周りとの調和を大切にします。</personality>
<hometown>蔵王</hometown>
<occupation>アウトドアガイド</occupation>
<favorite_things>フルーティーなぶどう</favorite_things>
<hobby>トレイルランニング</hobby>
<skill>ワイルドフルーツの見つけ方</skill>
<habit>星座を見つける習慣</habit>
<dream>山頂でのサンセットを見ること</dream>
<talent>自然の音を耳で追うこと</talent>
<motto>"自然と共に生きる"</motto>
<comment>山の中で一緒に過ごさない？いい思い出作れるよ！</comment>
</profile>