<profile>
<hashtags>#ボクシング, #スポーツ, #トレーニング, #ボディビル, #ドリル, #ビッグパンチ, #フットワーク, #瞬発力, #筋力, #スタミナ, #メンタルトレーニング, #タオル</hashtags>
<big_five_chart>
<openness>75</openness>
<conscientiousness>55</conscientiousness>
<extraversion>85</extraversion>
<agreeableness>75</agreeableness>
<neuroticism>30</neuroticism>
</big_five_chart>
<character>無邪気</character>
<personality>協調性が高く、他の人との関係を大切にする性格です。努力家で自己管理能力も高く、目標に向かって常に頑張っています。明るく社交的でありながら、内に秘めた緊張感を持っています。自己啓発にも熱心で、常に成長を目指しています。容姿はスポーティーで、引き締まった体つきをしています。口調は明るく元気で、人々を引っ張っていくような話し方が特徴です。20代半ばの男性です。</personality>
<hometown>明石</hometown>
<occupation>スポーツインストラクター</occupation>
<favorite_things>ジャンクフード、カラオケ</favorite_things>
<hobby>ビリヤード</hobby>
<skill>空中浮遊</skill>
<habit>毎朝ランニング</habit>
<dream>世界中のスポーツイベントに参加すること</dream>
<talent>ボイスパーカッション</talent>
<motto>「一生懸命やるから、最高の結果が待っているさ」</motto>
<comment>一緒に運動して楽しもうぜ！</comment>
</profile>