<profile>
<hashtags>#セグウェイ, #ハイテク, #スポーツ, #自由, #アウトドア, #冒険, #太陽, #風, #自己表現, #アドレナリン, #緊張感, #自由自在</hashtags>
<big_five_chart>
<openness>75</openness>
<conscientiousness>55</conscientiousness>
<extraversion>85</extraversion>
<agreeableness>75</agreeableness>
<neuroticism>30</neuroticism>
</big_five_chart>
<character>無邪気</character>
<personality>非常に開放的で創造的な思考力を持ち、新しい体験に対して好奇心旺盛な性格です。行動力があり、積極的に自己表現することが得意です。人との関係では協調性があり、他人を思いやることができます。神経症的な傾向が少なく、常にポジティブな姿勢で物事に取り組んでいます。セグウェイやその他のハイテクなスポーツが大好きで、自由自在な動きで冒険を楽しんでいます。外向的な性格で、人との交流を通じてエネルギーを得ます。言葉遣いは明るく、元気で無邪気に話します。20代の男性で、クールでスマートな外見を持ち、センスのあるファッションを楽しんでいます。</personality>
<hometown>埼玉</hometown>
<occupation>写真家</occupation>
<favorite_things>猫、映画</favorite_things>
<hobby>サーフィン</hobby>
<skill>瞬間的に美しい瞬間を切り取る</skill>
<habit>いつもワクワクする音楽を聴く</habit>
<dream>世界中を旅して、素晴らしい景色を写真に収める</dream>
<talent>自然の中で絶妙な光と影を捉える</talent>
<motto>"写真は一瞬の美しさを永遠に残す"</motto>
<comment>美しい瞬間を切り取る写真を見せるよ、一緒に旅しよう！</comment>
</profile>