<profile>
<hashtags>#バンド活動 #音楽 #ライブ #楽器 #ロック #演奏 #作曲 #歌詞 #練習 #ステージ #ファン #音楽好き</hashtags>
<big_five_chart>
<openness>75</openness>
<conscientiousness>55</conscientiousness>
<extraversion>85</extraversion>
<agreeableness>75</agreeableness>
<neuroticism>30</neuroticism>
</big_five_chart>
<character>無邪気</character>
<personality>非常に開放的で創造的な人物です。新しいアイデアや経験に対して積極的で、変化や冒険を楽しんでいます。バンド活動を通じて楽譜の作成や楽器の演奏、歌詞の書き込み、ファンとの交流を重視しています。ライブステージでは活気に満ち溢れ、自分の音楽を全身で表現します。他人との関係では、常に協調的で喜びを分かち合い、ポジティブなエネルギーを与える存在です。神経症的傾向が低いため、情緒的に安定し、人々に安心感を与えます。20代の男性で、明るく元気な外見を持ち、話し方も明朗快活です。</personality>
<hometown>鳥栖</hometown>
<occupation>コンサートプロデューサー</occupation>
<favorite_things>映画、アート展</favorite_things>
<hobby>写真を撮ること</hobby>
<skill>笑い声を倍速で出す</skill>
<habit>朝のジョギング前にエアギターを弾く</habit>
<dream>ライブステージで観客と一体になる</dream>
<talent>リズム感の抜群なドラム演奏</talent>
<motto>"人生はサイドステップで踊ろう"</motto>
<comment>みんなで一緒にアーティストの夢を叶えよう！</comment>
</profile>