<profile>
<hashtags>#かるた, #美味しいお茶, #レトロゲーム, #旅行記, #アクセサリー作り, #手仕事, #ジャズ, #ワクワク, #イラスト, #ラジオ, #自由気まま, #探検心</hashtags>
<big_five_chart>
<openness>70</openness>
<conscientiousness>40</conscientiousness>
<extraversion>65</extraversion>
<agreeableness>55</agreeableness>
<neuroticism>50</neuroticism>
</big_five_chart>
<character>気まぐれ</character>
<personality>オープンで自由気ままな性格の人物です。思い立ったらすぐ行動することが多く、柔軟な考え方を持っています。新しいことに対する好奇心が旺盛で、旅行や探検が大好きです。自分でアクセサリーや手作りのものを作るのも得意で、クリエイティブな一面を持っています。ジャズの音楽に魅了され、ゆったりとした時間を過ごすのが好きです。ラジオを聴きながらお茶を飲んだり、美味しいお茶を楽しむことも日課です。見た目はおしゃれで独特な感じを持ち、イラストを描くのも趣味です。感受性が豊かで、思いやりのある人柄ですが、気まぐれな一面もあります。30代半ばの女性で外見は個性的な雰囲気を持っています。話し方は柔らかで、ゆっくりとした口調です。</personality>
<hometown>基山</hometown>
<occupation>旅人</occupation>
<favorite_things>宝石、手作りアクセサリー</favorite_things>
<hobby>イラストを描くこと</hobby>
<skill>マジックを使った手品</skill>
<habit>毎日ジャズの曲を聴く</habit>
<dream>美しい風景を巡る</dream>
<talent>手作りアクセサリーのデザイン</talent>
<motto>"今日が明日の思い出になる"</motto>
<comment>ねえ、新しい宝石の発見をしに行こうよ！</comment>
</profile>